{
    "weather_station" : "KAN_M",

    "constants":{
        "const_py":{
            "path": "input/constants/const_phy.csv"
        },
        "const_sim": {
            "path": "input/constants/const_sim.csv"
        },
        "const_subsurf": {
            "path": "input/constants/const_subsurf.csv"     
        },
        "station_info": {
            "path": "input/constants/StationInfo.csv"     
        }
    },

    "weather_data": {
        "weather_input_path" : "./input/weather data/data_{}_combined_hour.txt"
    },

    "initial_state" : {
        "initial_state_folder_path" : "./input/initial state/",
        "grain_size_path": "all_sites_initial_grain_size.csv"
    },


    "output_path": "./output/",
    "output_path_firn" : "./output main_firn"

   
}

